Workbook

Sheet Summary
A1: NVIDIA Corporation - Valuation Summary
A2: Equity Research Valuation - September 2026
A4: Current Share Price | B4: =DCF!P35 -> 212.17
A6: Valuation Method | B6: Implied Price | C6: Reference | E6: DCF Valuation Bridge
A7: FCFF DCF | B7: =DCF!K26 -> 170.86128 | C7: Primary | E7: Enterprise Value | F7: =DCF!K21 -> 4.0612969e+09
A8: DDM | B8: =DDM!B7 -> 9.8514403 | C8: Secondary | E8: Cash & Investments | F8: =DCF!K22 -> 99369000
A9: Current Market Price | B9: =DCF!P35 -> 212.17 | C9: Market | E9: Debt | F9: =DCF!K23 -> 34366000
E10: Equity Value | F10: =DCF!K24 -> 4.1262999e+09
E11: Diluted Shares | F11: =DCF!K25 -> 24150000
A12: DCF Assumptions | E12: Implied Share Price | F12: =DCF!K26 -> 170.86128
A13: WACC | B13: =DCF!P12 -> 0.14086181
A14: 2027E Revenue Growth | B14: =DCF!G8 -> 0.9047
A15: 2028E Revenue Growth | B15: =DCF!H8 -> 0.6483 | E15: Valuation comparison
A16: 2029E Revenue Growth | B16: =DCF!I8 -> 0.3054 | E16: DCF Implied Price | F16: =DCF!K26 -> 170.86128
A17: 2030E Revenue Growth | B17: =DCF!J8 -> 0.2 | E17: DDM Implied Price | F17: =DDM!B7 -> 9.8514403
A18: 2031E Revenue Growth | B18: =DCF!K8 -> 0.12 | E18: Current Market Price | F18: =DCF!P35 -> 212.17
E19: DCF Upside/Downside | F19: =DCF!P36 -> -0.19469632
A21: DCF Sensitivity
A22: Base Case WACC | B22: =DCF!N7 -> 0.14086181
A23: Base Case Terminal Growth | B23: =DCF!M7 -> 0.04
A24: Base Case Implied Price | B24: =DCF!K26 -> 170.86128
A26: Valuation Interpretation

Sheet NVDA
A1: #VALUE! | M1: Quarter | N1: Date | O1: Shares Outstanding | P1: Net Income | Q1: Total sales | R1: Book Value
C2: Quarter | D2: {=_xlfn.STOCKHISTORY(A1,DATE(2020,4,27),TODAY(),0,1,0,1)} -> Date | E2: Close | F2: EPS | G2: Book Value | H2: Sales Per Share | I2: P/E Ratio | J2: P/B Ratio | K2: P/S Ratio | M2: 1Q2020 | N2: 43947 | O2: 24600000 | P2: 917000 | Q2: 3080000 | R2: 13100000
C3: =LOOKUP(D3,$N$2:$N$27,$M$2:$M$27) -> 1Q2020 | D3: 43948 | E3: 7.427 | F3: =VLOOKUP($C3,$M$2:$R$27,4,0)/VLOOKUP($C3,$M$2:$R$27,3,0) -> 0.037276423 | G3: =VLOOKUP($C3,$M$2:$R$27,6,0)/VLOOKUP($C3,$M$2:$R$27,3,0) -> 0.53252033 | H3: =VLOOKUP($C3,$M$2:$R$27,5,0)/VLOOKUP($C3,$M$2:$R$27,3,0) -> 0.12520325 | I3: =$E3/(F3*4) -> 49.810305 | J3: =$E3/(G3*4) -> 3.4867214 | K3: =$E3/(H3*4) -> 14.829886 | M3: 2Q2020 | N3: 44038 | O3: 24680000 | P3: 622000 | Q3: 3866000 | R3: 13910000
C4: =LOOKUP(D4,$N$2:$N$27,$M$2:$M$27) -> 1Q2020 | D4: 43949 | E4: 7.284 | F4: =VLOOKUP($C4,$M$2:$R$27,4,0)/VLOOKUP($C4,$M$2:$R$27,3,0) -> 0.037276423 | G4: =VLOOKUP($C4,$M$2:$R$27,6,0)/VLOOKUP($C4,$M$2:$R$27,3,0) -> 0.53252033 | H4: =VLOOKUP($C4,$M$2:$R$27,5,0)/VLOOKUP($C4,$M$2:$R$27,3,0) -> 0.12520325 | I4: =$E4/(F4*4) -> 48.851254 | J4: =$E4/(G4*4) -> 3.4195878 | K4: =$E4/(H4*4) -> 14.544351 | M4: 3Q2020 | N4: 44129 | O4: 24760000 | P4: 1336000 | Q4: 4726000 | R4: 15330000
C5: =LOOKUP(D5,$N$2:$N$27,$M$2:$M$27) -> 1Q2020 | D5: 43950 | E5: 7.4615 | F5: =VLOOKUP($C5,$M$2:$R$27,4,0)/VLOOKUP($C5,$M$2:$R$27,3,0) -> 0.037276423 | G5: =VLOOKUP($C5,$M$2:$R$27,6,0)/VLOOKUP($C5,$M$2:$R$27,3,0) -> 0.53252033 | H5: =VLOOKUP($C5,$M$2:$R$27,5,0)/VLOOKUP($C5,$M$2:$R$27,3,0) -> 0.12520325 | I5: =$E5/(F5*4) -> 50.041685 | J5: =$E5/(G5*4) -> 3.5029179 | K5: =$E5/(H5*4) -> 14.898774 | M5: 4Q2020 | N5: 44227 | O5: 24800000 | P5: 1457000 | Q5: 5003000 | R5: 16890000
C6: =LOOKUP(D6,$N$2:$N$27,$M$2:$M$27) -> 1Q2020 | D6: 43951 | E6: 7.307 | F6: =VLOOKUP($C6,$M$2:$R$27,4,0)/VLOOKUP($C6,$M$2:$R$27,3,0) -> 0.037276423 | G6: =VLOOKUP($C6,$M$2:$R$27,6,0)/VLOOKUP($C6,$M$2:$R$27,3,0) -> 0.53252033 | H6: =VLOOKUP($C6,$M$2:$R$27,5,0)/VLOOKUP($C6,$M$2:$R$27,3,0) -> 0.12520325 | I6: =$E6/(F6*4) -> 49.005507 | J6: =$E6/(G6*4) -> 3.4303855 | K6: =$E6/(H6*4) -> 14.590276 | M6: 1Q2021 | N6: 44318 | O6: 24920000 | P6: 1912000 | Q6: 5661000 | R6: 18770000
C7: =LOOKUP(D7,$N$2:$N$27,$M$2:$M$27) -> 1Q2020 | D7: 43952 | E7: 7.0695 | F7: =VLOOKUP($C7,$M$2:$R$27,4,0)/VLOOKUP($C7,$M$2:$R$27,3,0) -> 0.037276423 | G7: =VLOOKUP($C7,$M$2:$R$27,6,0)/VLOOKUP($C7,$M$2:$R$27,3,0) -> 0.53252033 | H7: =VLOOKUP($C7,$M$2:$R$27,5,0)/VLOOKUP($C7,$M$2:$R$27,3,0) -> 0.12520325 | I7: =$E7/(F7*4) -> 47.412677 | J7: =$E7/(G7*4) -> 3.3188874 | K7: =$E7/(H7*4) -> 14.116047 | M7: 2Q2021 | N7: 44409 | O7: 24960000 | P7: 2374000 | Q7: 6507000 | R7: 21150000
C8: =LOOKUP(D8,$N$2:$N$27,$M$2:$M$27) -> 1Q2020 | D8: 43955 | E8: 7.2821 | F8: =VLOOKUP($C8,$M$2:$R$27,4,0)/VLOOKUP($C8,$M$2:$R$27,3,0) -> 0.037276423 | G8: =VLOOKUP($C8,$M$2:$R$27,6,0)/VLOOKUP($C8,$M$2:$R$27,3,0) -> 0.53252033 | H8: =VLOOKUP($C8,$M$2:$R$27,5,0)/VLOOKUP($C8,$M$2:$R$27,3,0) -> 0.12520325 | I8: =$E8/(F8*4) -> 48.838511 | J8: =$E8/(G8*4) -> 3.4186958 | K8: =$E8/(H8*4) -> 14.540557 | M8: 3Q2021 | N8: 44500 | O8: 25020000 | P8: 2464000 | Q8: 7103000 | R8: 23800000
C9: =LOOKUP(D9,$N$2:$N$27,$M$2:$M$27) -> 1Q2020 | D9: 43956 | E9: 7.3435 | F9: =VLOOKUP($C9,$M$2:$R$27,4,0)/VLOOKUP($C9,$M$2:$R$27,3,0) -> 0.037276423 | G9: =VLOOKUP($C9,$M$2:$R$27,6,0)/VLOOKUP($C9,$M$2:$R$27,3,0) -> 0.53252033 | H9: =VLOOKUP($C9,$M$2:$R$27,5,0)/VLOOKUP($C9,$M$2:$R$27,3,0) -> 0.12520325 | I9: =$E9/(F9*4) -> 49.2503 | J9: =$E9/(G9*4) -> 3.447521 | K9: =$E9/(H9*4) -> 14.663157 | M9: 4Q2021 | N9: 44591 | O9: 25060000 | P9: 3002000 | Q9: 7643000 | R9: 26610000
C10: =LOOKUP(D10,$N$2:$N$27,$M$2:$M$27) -> 1Q2020 | D10: 43957 | E10: 7.4448 | F10: =VLOOKUP($C10,$M$2:$R$27,4,0)/VLOOKUP($C10,$M$2:$R$27,3,0) -> 0.037276423 | G10: =VLOOKUP($C10,$M$2:$R$27,6,0)/VLOOKUP($C10,$M$2:$R$27,3,0) -> 0.53252033 | H10: =VLOOKUP($C10,$M$2:$R$27,5,0)/VLOOKUP($C10,$M$2:$R$27,3,0) -> 0.12520325 | I10: =$E10/(F10*4) -> 49.929684 | J10: =$E10/(G10*4) -> 3.4950779 | K10: =$E10/(H10*4) -> 14.865429 | M10: 1Q2022 | N10: 44682 | O10: 25040000 | P10: 1618000 | Q10: 8288000 | R10: 26320000
C11: =LOOKUP(D11,$N$2:$N$27,$M$2:$M$27) -> 1Q2020 | D11: 43958 | E11: 7.6218 | F11: =VLOOKUP($C11,$M$2:$R$27,4,0)/VLOOKUP($C11,$M$2:$R$27,3,0) -> 0.037276423 | G11: =VLOOKUP($C11,$M$2:$R$27,6,0)/VLOOKUP($C11,$M$2:$R$27,3,0) -> 0.53252033 | H11: =VLOOKUP($C11,$M$2:$R$27,5,0)/VLOOKUP($C11,$M$2:$R$27,3,0) -> 0.12520325 | I11: =$E11/(F11*4) -> 51.116761 | J11: =$E11/(G11*4) -> 3.5781733 | K11: =$E11/(H11*4) -> 15.218854 | M11: 2Q2022 | N11: 44773 | O11: 24890000 | P11: 656000 | Q11: 6704000 | R11: 23850000
C12: =LOOKUP(D12,$N$2:$N$27,$M$2:$M$27) -> 1Q2020 | D12: 43959 | E12: 7.8125 | F12: =VLOOKUP($C12,$M$2:$R$27,4,0)/VLOOKUP($C12,$M$2:$R$27,3,0) -> 0.037276423 | G12: =VLOOKUP($C12,$M$2:$R$27,6,0)/VLOOKUP($C12,$M$2:$R$27,3,0) -> 0.53252033 | H12: =VLOOKUP($C12,$M$2:$R$27,5,0)/VLOOKUP($C12,$M$2:$R$27,3,0) -> 0.12520325 | I12: =$E12/(F12*4) -> 52.39572 | J12: =$E12/(G12*4) -> 3.6677004 | K12: =$E12/(H12*4) -> 15.599635 | M12: 3Q2022 | N12: 44864 | O12: 24680000 | P12: 680000 | Q12: 5931000 | R12: 21350000
C13: =LOOKUP(D13,$N$2:$N$27,$M$2:$M$27) -> 1Q2020 | D13: 43962 | E13: 8.0655 | F13: =VLOOKUP($C13,$M$2:$R$27,4,0)/VLOOKUP($C13,$M$2:$R$27,3,0) -> 0.037276423 | G13: =VLOOKUP($C13,$M$2:$R$27,6,0)/VLOOKUP($C13,$M$2:$R$27,3,0) -> 0.53252033 | H13: =VLOOKUP($C13,$M$2:$R$27,5,0)/VLOOKUP($C13,$M$2:$R$27,3,0) -> 0.12520325 | I13: =$E13/(F13*4) -> 54.092503 | J13: =$E13/(G13*4) -> 3.7864752 | K13: =$E13/(H13*4) -> 16.104813 | M13: 4Q2022 | N13: 44955 | O13: 24660000 | P13: 1414000 | Q13: 6051000 | R13: 22100000
C14: =LOOKUP(D14,$N$2:$N$27,$M$2:$M$27) -> 1Q2020 | D14: 43963 | E14: 7.8025 | F14: =VLOOKUP($C14,$M$2:$R$27,4,0)/VLOOKUP($C14,$M$2:$R$27,3,0) -> 0.037276423 | G14: =VLOOKUP($C14,$M$2:$R$27,6,0)/VLOOKUP($C14,$M$2:$R$27,3,0) -> 0.53252033 | H14: =VLOOKUP($C14,$M$2:$R$27,5,0)/VLOOKUP($C14,$M$2:$R$27,3,0) -> 0.12520325 | I14: =$E14/(F14*4) -> 52.328653 | J14: =$E14/(G14*4) -> 3.6630057 | K14: =$E14/(H14*4) -> 15.579667 | M14: 1Q2023 | N14: 45046 | O14: 24730000 | P14: 2043000 | Q14: 7192000 | R14: 24520000
... C27: =LOOKUP(D27,$N$2:$N$27,$M$2:$M$27) -> 1Q2020 | D27: 43983 | E27: 8.8063 | F27: =VLOOKUP($C27,$M$2:$R$27,4,0)/VLOOKUP($C27,$M$2:$R$27,3,0) -> 0.037276423 | G27: =VLOOKUP($C27,$M$2:$R$27,6,0)/VLOOKUP($C27,$M$2:$R$27,3,0) -> 0.53252033 | H27: =VLOOKUP($C27,$M$2:$R$27,5,0)/VLOOKUP($C27,$M$2:$R$27,3,0) -> 0.12520325 | I27: =$E27/(F27*4) -> 59.060791 | J27: =$E27/(G27*4) -> 4.1342553 | K27: =$E27/(H27*4) -> 17.584008 | M27: 2Q2026 | N27: 46229 | O27: 24150000 | P27: 59688000 | Q27: 96221000 | R27: 228980000
C28: =LOOKUP(D28,$N$2:$N$27,$M$2:$M$27) -> 1Q2020 | D28: 43984 | E28: 8.8253 | F28: =VLOOKUP($C28,$M$2:$R$27,4,0)/VLOOKUP($C28,$M$2:$R$27,3,0) -> 0.037276423 | G28: =VLOOKUP($C28,$M$2:$R$27,6,0)/VLOOKUP($C28,$M$2:$R$27,3,0) -> 0.53252033 | H28: =VLOOKUP($C28,$M$2:$R$27,5,0)/VLOOKUP($C28,$M$2:$R$27,3,0) -> 0.12520325 | I28: =$E28/(F28*4) -> 59.188217 | J28: =$E28/(G28*4) -> 4.1431752 | K28: =$E28/(H28*4) -> 17.621946
C29: =LOOKUP(D29,$N$2:$N$27,$M$2:$M$27) -> 1Q2020 | D29: 43985 | E29: 8.7695 | F29: =VLOOKUP($C29,$M$2:$R$27,4,0)/VLOOKUP($C29,$M$2:$R$27,3,0) -> 0.037276423 | G29: =VLOOKUP($C29,$M$2:$R$27,6,0)/VLOOKUP($C29,$M$2:$R$27,3,0) -> 0.53252033 | H29: =VLOOKUP($C29,$M$2:$R$27,5,0)/VLOOKUP($C29,$M$2:$R$27,3,0) -> 0.12520325 | I29: =$E29/(F29*4) -> 58.813986 | J29: =$E29/(G29*4) -> 4.116979 | K29: =$E29/(H29*4) -> 17.510528
C30: =LOOKUP(D30,$N$2:$N$27,$M$2:$M$27) -> 1Q2020 | D30: 43986 | E30: 8.7665 | F30: =VLOOKUP($C30,$M$2:$R$27,4,0)/VLOOKUP($C30,$M$2:$R$27,3,0) -> 0.037276423 | G30: =VLOOKUP($C30,$M$2:$R$27,6,0)/VLOOKUP($C30,$M$2:$R$27,3,0) -> 0.53252033 | H30: =VLOOKUP($C30,$M$2:$R$27,5,0)/VLOOKUP($C30,$M$2:$R$27,3,0) -> 0.12520325 | I30: =$E30/(F30*4) -> 58.793866 | J30: =$E30/(G30*4) -> 4.1155706 | K30: =$E30/(H30*4) -> 17.504537
C31: =LOOKUP(D31,$N$2:$N$27,$M$2:$M$27) -> 1Q2020 | D31: 43987 | E31: 8.92 | F31: =VLOOKUP($C31,$M$2:$R$27,4,0)/VLOOKUP($C31,$M$2:$R$27,3,0) -> 0.037276423 | G31: =VLOOKUP($C31,$M$2:$R$27,6,0)/VLOOKUP($C31,$M$2:$R$27,3,0) -> 0.53252033 | H31: =VLOOKUP($C31,$M$2:$R$27,5,0)/VLOOKUP($C31,$M$2:$R$27,3,0) -> 0.12520325 | I31: =$E31/(F31*4) -> 59.823337 | J31: =$E31/(G31*4) -> 4.1876336 | K31: =$E31/(H31*4) -> 17.811039
C32: =LOOKUP(D32,$N$2:$N$27,$M$2:$M$27) -> 1Q2020 | D32: 43990 | E32: 8.805 | F32: =VLOOKUP($C32,$M$2:$R$27,4,0)/VLOOKUP($C32,$M$2:$R$27,3,0) -> 0.037276423 | G32: =VLOOKUP($C32,$M$2:$R$27,6,0)/VLOOKUP($C32,$M$2:$R$27,3,0) -> 0.53252033 | H32: =VLOOKUP($C32,$M$2:$R$27,5,0)/VLOOKUP($C32,$M$2:$R$27,3,0) -> 0.12520325 | I32: =$E32/(F32*4) -> 59.052072 | J32: =$E32/(G32*4) -> 4.133645 | K32: =$E32/(H32*4) -> 17.581412
C33: =LOOKUP(D33,$N$2:$N$27,$M$2:$M$27) -> 1Q2020 | D33: 43991 | E33: 9.046 | F33: =VLOOKUP($C33,$M$2:$R$27,4,0)/VLOOKUP($C33,$M$2:$R$27,3,0) -> 0.037276423 | G33: =VLOOKUP($C33,$M$2:$R$27,6,0)/VLOOKUP($C33,$M$2:$R$27,3,0) -> 0.53252033 | H33: =VLOOKUP($C33,$M$2:$R$27,5,0)/VLOOKUP($C33,$M$2:$R$27,3,0) -> 0.12520325 | I33: =$E33/(F33*4) -> 60.668375 | J33: =$E33/(G33*4) -> 4.2467863 | K33: =$E33/(H33*4) -> 18.06263
C34: =LOOKUP(D34,$N$2:$N$27,$M$2:$M$27) -> 1Q2020 | D34: 43992 | E34: 9.3668 | F34: =VLOOKUP($C34,$M$2:$R$27,4,0)/VLOOKUP($C34,$M$2:$R$27,3,0) -> 0.037276423 | G34: =VLOOKUP($C34,$M$2:$R$27,6,0)/VLOOKUP($C34,$M$2:$R$27,3,0) -> 0.53252033 | H34: =VLOOKUP($C34,$M$2:$R$27,5,0)/VLOOKUP($C34,$M$2:$R$27,3,0) -> 0.12520325 | I34: =$E34/(F34*4) -> 62.819869 | J34: =$E34/(G34*4) -> 4.3973908 | K34: =$E34/(H34*4) -> 18.703188
C35: =LOOKUP(D35,$N$2:$N$27,$M$2:$M$27) -> 1Q2020 | D35: 43993 | E35: 8.7963 | F35: =VLOOKUP($C35,$M$2:$R$27,4,0)/VLOOKUP($C35,$M$2:$R$27,3,0) -> 0.037276423 | G35: =VLOOKUP($C35,$M$2:$R$27,6,0)/VLOOKUP($C35,$M$2:$R$27,3,0) -> 0.53252033 | H35: =VLOOKUP($C35,$M$2:$R$27,5,0)/VLOOKUP($C35,$M$2:$R$27,3,0) -> 0.12520325 | I35: =$E35/(F35*4) -> 58.993724 | J35: =$E35/(G35*4) -> 4.1295607 | K35: =$E35/(H35*4) -> 17.564041
C36: =LOOKUP(D36,$N$2:$N$27,$M$2:$M$27) -> 1Q2020 | D36: 43994 | E36: 8.9325 | F36: =VLOOKUP($C36,$M$2:$R$27,4,0)/VLOOKUP($C36,$M$2:$R$27,3,0) -> 0.037276423 | G36: =VLOOKUP($C36,$M$2:$R$27,6,0)/VLOOKUP($C36,$M$2:$R$27,3,0) -> 0.53252033 | H36: =VLOOKUP($C36,$M$2:$R$27,5,0)/VLOOKUP($C36,$M$2:$R$27,3,0) -> 0.12520325 | I36: =$E36/(F36*4) -> 59.90717 | J36: =$E36/(G36*4) -> 4.1935019 | K36: =$E36/(H36*4) -> 17.835998
C37: =LOOKUP(D37,$N$2:$N$27,$M$2:$M$27) -> 1Q2020 | D37: 43997 | E37: 9.1738 | F37: =VLOOKUP($C37,$M$2:$R$27,4,0)/VLOOKUP($C37,$M$2:$R$27,3,0) -> 0.037276423 | G37: =VLOOKUP($C37,$M$2:$R$27,6,0)/VLOOKUP($C37,$M$2:$R$27,3,0) -> 0.53252033 | H37: =VLOOKUP($C37,$M$2:$R$27,5,0)/VLOOKUP($C37,$M$2:$R$27,3,0) -> 0.12520325 | I37: =$E37/(F37*4) -> 61.525485 | J37: =$E37/(G37*4) -> 4.306784 | K37: =$E37/(H37*4) -> 18.317815
C38: =LOOKUP(D38,$N$2:$N$27,$M$2:$M$27) -> 1Q2020 | D38: 43998 | E38: 9.0685 | F38: =VLOOKUP($C38,$M$2:$R$27,4,0)/VLOOKUP($C38,$M$2:$R$27,3,0) -> 0.037276423 | G38: =VLOOKUP($C38,$M$2:$R$27,6,0)/VLOOKUP($C38,$M$2:$R$27,3,0) -> 0.53252033 | H38: =VLOOKUP($C38,$M$2:$R$27,5,0)/VLOOKUP($C38,$M$2:$R$27,3,0) -> 0.12520325 | I38: =$E38/(F38*4) -> 60.819275 | J38: =$E38/(G38*4) -> 4.2573492 | K38: =$E38/(H38*4) -> 18.107557
C39: =LOOKUP(D39,$N$2:$N$27,$M$2:$M$27) -> 1Q2020 | D39: 43999 | E39: 9.236 | F39: =VLOOKUP($C39,$M$2:$R$27,4,0)/VLOOKUP($C39,$M$2:$R$27,3,0) -> 0.037276423 | G39: =VLOOKUP($C39,$M$2:$R$27,6,0)/VLOOKUP($C39,$M$2:$R$27,3,0) -> 0.53252033 | H39: =VLOOKUP($C39,$M$2:$R$27,5,0)/VLOOKUP($C39,$M$2:$R$27,3,0) -> 0.12520325 | I39: =$E39/(F39*4) -> 61.942639 | J39: =$E39/(G39*4) -> 4.3359847 | K39: =$E39/(H39*4) -> 18.442013
... C1601: =LOOKUP(D1601,$N$2:$N$27,$M$2:$M$27) -> 2Q2026 | D1601: 46269 | E1601: 230.36 | F1601: =VLOOKUP($C1601,$M$2:$R$27,4,0)/VLOOKUP($C1601,$M$2:$R$27,3,0) -> 2.4715528 | G1601: =VLOOKUP($C1601,$M$2:$R$27,6,0)/VLOOKUP($C1601,$M$2:$R$27,3,0) -> 9.4815735 | H1601: =VLOOKUP($C1601,$M$2:$R$27,5,0)/VLOOKUP($C1601,$M$2:$R$27,3,0) -> 3.9843064 | I1601: =$E1601/(F1601*4) -> 23.301141 | J1601: =$E1601/(G1601*4) -> 6.0738864 | K1601: =$E1601/(H1601*4) -> 14.45421
D1602: 46273 | E1602: 225.73
D1603: 46274 | E1603: 223.67
D1604: 46275 | E1604: 218.36
D1605: 46276 | E1605: 218.29
D1606: 46279 | E1606: 210.96
D1607: 46280 | E1607: 212.17
D1608: 46281 | E1608: 213.9

Sheet DCF
A1: NVIDIA Corporation - DCF Valuation
A2: Historical & Forecast Free Cash Flow to Firm in thousands, except per-share data
A3: Fiscal Year Ending January
A4: Valuation Date: September 2026
A5: Market price and market-based assumptions as of September 2026 | D5: Historical | I5: Estimates
B6: 2022A | C6: 2023A | D6: 2024A | E6: 2025A | F6: 2026A | G6: 2027E | H6: 2028E | I6: 2029E | J6: 2030E | K6: 2031E | M6: Terminal Growth | N6: WACC | O6: Risk free rate | P6: 0.0496
A7: Revenue | B7: 26914000 | C7: 26974000 | D7: 60922000 | E7: 130497000 | F7: 215938000 | G7: =F7*(1+G8) -> 4.1129711e+08 | H7: =G7*(1+H8) -> 6.7794102e+08 | I7: =H7*(1+I8) -> 8.8498421e+08 | J7: =I7*(1+J8) -> 1.0619811e+09 | K7: =J7*(1+K8) -> 1.1894188e+09 | M7: 0.04 | N7: =P15*P9+P16*P10*(1-P11) -> 0.14086181 | O7: Beta | P7: 2.22
A8: Revenue Growth | C8: =C7/B7-1 -> 0.002229323 | D8: =D7/C7-1 -> 1.2585453 | E8: =E7/D7-1 -> 1.1420341 | F8: =F7/E7-1 -> 0.65473536 | G8: 0.9047 | H8: 0.6483 | I8: 0.3054 | J8: 0.2 | K8: 0.12 | O8: Equity Risk Premium | P8: 0.0414
A9: EBIT | B9: 10041000 | C9: 4224000 | D9: 32972000 | E9: 81453000 | F9: 130390000 | G9: =G7*G10 -> 2.5500421e+08 | H9: =H7*H10 -> 4.2032343e+08 | I9: =I7*I10 -> 5.3984037e+08 | J9: =J7*J10 -> 6.3718863e+08 | K9: =K7*K10 -> 6.8986289e+08 | O9: Cost of Equity | P9: =P6+P7*P8 -> 0.141508
A10: EBIT Margin | B10: =B9/B7 -> 0.37307721 | C10: =C9/C7 -> 0.15659524 | D10: =D9/D7 -> 0.54121664 | E10: =E9/E7 -> 0.62417527 | F10: =F9/F7 -> 0.60383073 | G10: 0.62 | H10: 0.62 | I10: 0.61 | J10: 0.6 | K10: 0.58 | O10: Pre-Tax Cost of Debt | P10: 0.05
A11: Tax Rate | B11: 0.019 | C11: -0.045 | D11: 0.12 | E11: 0.133 | F11: 0.151 | G11: 0.165 | H11: 0.17 | I11: 0.175 | J11: 0.18 | K11: 0.18 | O11: Tax Rate | P11: 0.165
A12: NOPAT | B12: =B9*(1-B11) -> 9850221 | C12: =C9*(1-C11) -> 4414080 | D12: =D9*(1-D11) -> 29015360 | E12: =E9*(1-E11) -> 70619751 | F12: =F9*(1-F11) -> 110701110 | G12: =G9*(1-G11) -> 2.1292851e+08 | H12: =H9*(1-H11) -> 3.4886845e+08 | I12: =I9*(1-I11) -> 4.4536831e+08 | ... K12: =K9*(1-K11) -> 5.6568757e+08 | O12: WACC | P12: =P15*P9+P16*P10*(1-P11) -> 0.14086181
A13: D&A | B13: 1174000 | C13: 1544000 | D13: 1508000 | E13: 1864000 | F13: 2843000 | G13: =G7*1.4% -> 5758159.5 | H13: =H7*1.4% -> 9491174.3 | I13: =I7*1.4% -> 12389779 | J13: =J7*1.4% -> 14867735 | K13: =K7*1.4% -> 16651863 | O13: Market Value of Equity | P13: 5271000000
A14: Capex | B14: 976000 | C14: 1833000 | D14: 1069000 | E14: 3236000 | F14: 6042000 | G14: =G7*4% -> 16451884 | H14: =H7*3.5% -> 23727936 | I14: =I7*3% -> 26549526 | J14: =J7*2.75% -> 29204479 | K14: =K7*2.5% -> 29735470 | O14: Market Value of Debt | P14: 34366000
A15: Change in NWC | B15: 1718000 | C15: 1178000 | D15: 4516000 | E15: 9809000 | F15: 13096000 | G15: =G7*14.5%-F7*14.77% -> 27744038 | H15: =H7*14.5%-G7*14.5% -> 38663368 | I15: =I7*14.5%-H7*14.5% -> 30021262 | J15: =J7*14.5%-I7*14.5% -> 25664542 | K15: =K7*14.5%-J7*14.5% -> 18478470 | O15: Equity Weight | P15: =P13/(P13+P14) -> 0.99352241
A16: FCFF | B16: =B12+B13-B14-B15 -> 8330221 | C16: =C12+C13-C14-C15 -> 2947080 | D16: =D12+D13-D14-D15 -> 24938360 | E16: =E12+E13-E14-E15 -> 59438751 | F16: =F12+F13-F14-F15 -> 94406110 | G16: =G12+G13-G14-G15 -> 1.7449075e+08 | H16: =H12+H13-H14-H15 -> 2.9596832e+08 | I16: =I12+I13-I14-I15 -> 4.011873e+08 | ... K16: =K12+K13-K14-K15 -> 5.341255e+08 | O16: Debt Weight | P16: =P14/(P13+P14) -> 0.0064775927
A17: VALUATION
A18: Discount Factor | G18: =1/(1+$N$7)^1 -> 0.87653035 | H18: =1/(1+$N$7)^2 -> 0.76830545 | I18: =1/(1+$N$7)^3 -> 0.67344305 | J18: =1/(1+$N$7)^4 -> 0.59029327 | K18: =1/(1+$N$7)^5 -> 0.51740997
A19: PV of FCFF | G19: =G16*G18 -> 1.5294644e+08 | H19: =H16*H18 -> 2.2739408e+08 | I19: =I16*I18 -> 2.701768e+08 | J19: =J16*J18 -> 2.848126e+08 | K19: =K16*K18 -> 2.7636186e+08
A20: Terminal Value | K20: =K16*(1+$M$7)/($N$7-$M$7) -> 5.5074416e+09 | O20: Base Case Implied Share Price | Q20: Terminal Growth/WACC
A21: Enterprise Value | K21: =SUM(G19:K19)+K20*K18 -> 4.0612969e+09 | O21: =K26 -> 170.86128 | P21: 0.12 | Q21: 0.13 | R21: 0.14 | S21: 0.15 | T21: 0.16
A22: Cash and Investments | K22: 99369000 | O22: 0.02 | P22: 183.99159 | Q22: 165.76624 | R22: 150.62709 | S22: 137.8601 | T22: 126.9553
A23: Debt | K23: 34366000 | O23: 0.03 | P23: 199.6091 | Q23: 178.09785 | R23: 160.54758 | S23: 145.96616 | T23: 133.66685
A24: Equity Value | K24: =K21+K22-K23 -> 4.1262999e+09 | O24: 0.04 | P24: 219.13097 | Q24: 193.16981 | R24: 172.45216 | S24: 155.54606 | T24: 141.49699
A25: Diluted Shares | K25: 24150000 | O25: 0.05 | P25: 244.23053 | Q25: 212.00977 | R25: 187.0022 | S25: 167.04194 | T25: 150.75079
A26: Implied Share Price | K26: =K24/K25 -> 170.86128 | O26: 0.06 | P26: 277.69661 | Q26: 236.23257 | R26: 205.18975 | S26: 181.09246 | T26: 161.85536
O29: Valuation Summary
O30: Enterprise Value | P30: =K21 -> 4.0612969e+09
O31: Cash & Investments | P31: =K22 -> 99369000
O32: Debt | P32: =K23 -> 34366000
O33: Equity Value | P33: =K24 -> 4.1262999e+09
O34: Implied Share Price | P34: =K26 -> 170.86128
O35: Current Share Price | P35: 212.17
O36: Upside/Downside | P36: =P34/P35-1 -> -0.19469632

Sheet DDM
A1: Dividend Discount Model
A2: Secondary Cross Check
A4: Dividend Next Year | B4: =0.25*4 -> 1
A5: Growth Rate | B5: 0.04
A6: Discount rate | B6: =DCF!P9 -> 0.141508
A7: DDM Valuation | B7: =B4/(B6-B5) -> 9.8514403
